README.md
setup.cfg
setup.py
eis/__init__.py
eis/customer/__init__.py
eis/customer/api_client.py
eis/customer/configuration.py
eis/customer/exceptions.py
eis/customer/model_utils.py
eis/customer/rest.py
eis/customer/api/__init__.py
eis/customer/api/authentication_api.py
eis/customer/api/claims_api.py
eis/customer/api/customers_api.py
eis/customer/api/default_api.py
eis/customer/api/documents_api.py
eis/customer/api/invites_api.py
eis/customer/api/invoices_api.py
eis/customer/api/leads_api.py
eis/customer/api/payments_api.py
eis/customer/api/policies_api.py
eis/customer/api/products_api.py
eis/customer/apis/__init__.py
eis/customer/model/__init__.py
eis/customer/model/account_class.py
eis/customer/model/account_policy_class.py
eis/customer/model/authentication_result_class.py
eis/customer/model/bank_transfer_dto.py
eis/customer/model/billing_address_dto.py
eis/customer/model/card_details_dto.py
eis/customer/model/change_customer_email_request_dto.py
eis/customer/model/change_password_request_dto.py
eis/customer/model/change_password_response_class.py
eis/customer/model/claim_class.py
eis/customer/model/complete_adyen_payment_setup_request_dto.py
eis/customer/model/complete_braintree_payment_setup_request_dto.py
eis/customer/model/complete_eis_payment_setup_request_dto.py
eis/customer/model/complete_payment_setup_psp_request.py
eis/customer/model/complete_payment_setup_response_class.py
eis/customer/model/complete_stripe_payment_setup_request_dto.py
eis/customer/model/create_account_request_dto.py
eis/customer/model/create_bank_account_request_dto.py
eis/customer/model/create_customer_claim_request_dto.py
eis/customer/model/create_customer_claim_response_class.py
eis/customer/model/create_customer_request_dto.py
eis/customer/model/create_customer_response_class.py
eis/customer/model/create_lead_request_dto.py
eis/customer/model/create_lead_response_class.py
eis/customer/model/create_policy_request_dto.py
eis/customer/model/create_presigned_post_response_class.py
eis_customers.egg-info/PKG-INFO
eis_customers.egg-info/SOURCES.txt
eis_customers.egg-info/dependency_links.txt
eis_customers.egg-info/requires.txt
eis_customers.egg-info/top_level.txt
