Metadata-Version: 2.1
Name: eis-customers
Version: 1.32.0
Summary: EMIL CustomerService
Home-page: UNKNOWN
Author: Contact us
Author-email: kontakt@emil.de
License: UNKNOWN
Keywords: OpenAPI,OpenAPI-Generator,EMIL CustomerService
Platform: UNKNOWN
Requires-Python: >=3.6
